{
  "id": "weekly-map/weeks-1-13",
  "title": "Weekly Learning Map",
  "description": "This document outlines the structured, week-by-week curriculum for the Physical AI & Humanoid Robotics course. Each section details the lessons, key learning objectives, and expected assessments.",
  "source": "@site/docs/weekly-map/weeks-1-13.md",
  "sourceDirName": "weekly-map",
  "slug": "/weekly-map/weeks-1-13",
  "permalink": "/physical-ai-textbook/weekly-map/weeks-1-13",
  "draft": false,
  "unlisted": false,
  "editUrl": "https://github.com/your-github-username/ai-book/tree/main/docs/weekly-map/weeks-1-13.md",
  "tags": [],
  "version": "current",
  "frontMatter": {
    "id": "weeks-1-13",
    "title": "Weekly Learning Map",
    "sidebar_label": "Weeks 1-13"
  },
  "sidebar": "tutorialSidebar",
  "previous": {
    "title": "Future Trends",
    "permalink": "/physical-ai-textbook/modules/08-future-trends"
  },
  "next": {
    "title": "Hardware Setup",
    "permalink": "/physical-ai-textbook/hardware/setup"
  }
}